psychometric_tests/__init__.py
psychometric_tests/defs.py
psychometric_tests/entry.py
psychometric_tests/settings.json
psychometric_tests/anagram/__init__.py
psychometric_tests/anagram/main.py
psychometric_tests/anagram/setup.py
psychometric_tests/anagram/widget.py
psychometric_tests/anagram/anagram_ques/5文字.csv
psychometric_tests/anagram/anagram_ques/6文字.csv
psychometric_tests/anagram/anagram_ques/8_letters.csv
psychometric_tests/ant/__init__.py
psychometric_tests/ant/main.py
psychometric_tests/ant/setup.py
psychometric_tests/ant/widget.py
psychometric_tests/nback/__init__.py
psychometric_tests/nback/generate_sum_ques.py
psychometric_tests/nback/main.py
psychometric_tests/nback/setup.py
psychometric_tests/nback/widget.py
psychometric_tests/nback/stimulus/1digit(1-9).csv
psychometric_tests/nback/stimulus/2digit(10-99).csv
psychometric_tests/nback/stimulus/A-Z.csv
psychometric_tests/nback/stimulus/sum.csv
psychometric_tests/nback/stimulus/sum_1digit_ans.csv
psychometric_tests/nback/stimulus/words.csv
psychometric_tests/rat/__init__.py
psychometric_tests/rat/main.py
psychometric_tests/rat/setup.py
psychometric_tests/rat/widget.py
psychometric_tests/rat/remote_associates/bowden_and_jung-beeman.csv
psychometric_tests/rat/remote_associates/terai_miwa_and_asami.csv
psychometric_tests/resource/anagram.svg
psychometric_tests/resource/ant.svg
psychometric_tests/resource/nback.svg
psychometric_tests/resource/options.ico
psychometric_tests/resource/options.svg
psychometric_tests/resource/rat.svg
psychometric_tests/resource/results.svg
psychometric_tests/resource/settings.svg
psychometric_tests/resource/setup.svg
psychometric_tests/shared/__init__.py
psychometric_tests/shared/colours.py
psychometric_tests/shared/misc_funcs.py
psychometric_tests/shared/results_dialog.py
psychometric_tests/shared/setup_dialog.py
psychometric_tests-0.1.1.dist-info/LICENSE
psychometric_tests-0.1.1.dist-info/METADATA
psychometric_tests-0.1.1.dist-info/WHEEL
psychometric_tests-0.1.1.dist-info/entry_points.txt
psychometric_tests-0.1.1.dist-info/top_level.txt
psychometric_tests-0.1.1.dist-info/RECORD
