Metadata-Version: 2.1
Name: psychometric-tests
Version: 0.1.1
Summary: A python implementation of Attention Network Test (ANT), Remote Associates Test (RAT), an N-Back task, and an Anagram task.
Home-page: https://wlyeoh.gitlab.io/psychometric-tests/
Author: WL Yeoh
Author-email: wenliangyeoh@kyudai.jp
License: UNKNOWN
Project-URL: Source, https://gitlab.com/wlyeoh/psychometric-tests
Platform: UNKNOWN
Classifier: Programming Language :: Python :: 3
Classifier: License :: OSI Approved :: MIT License
Classifier: Operating System :: OS Independent
Requires-Python: >=3.6
License-File: LICENSE
Requires-Dist: PySide6
